mochila/__init__.py
mochila/__version.py
mochila/mochila.py
mochila-0.2.4.dist-info/DESCRIPTION.rst
mochila-0.2.4.dist-info/METADATA
mochila-0.2.4.dist-info/RECORD
mochila-0.2.4.dist-info/WHEEL
mochila-0.2.4.dist-info/metadata.json
mochila-0.2.4.dist-info/top_level.txt
