Metadata-Version: 2.0
Name: mochila
Version: 0.2.4
Summary: Provides collections and a powerful API to process data in those collections in a declarative way.
Home-page: http://bitbucket.org/arcanefoam/mochila
Author: Horacio Hoyos Rodriguez
Author-email: arcanefoam@gmail.com
License: UNKNOWN
Platform: any
Classifier: Programming Language :: Python
Classifier: Development Status :: 5 - Production/Stable
Classifier: Natural Language :: English
Classifier: Intended Audience :: Developers
Classifier: License :: OSI Approved :: Apache Software License
Classifier: Operating System :: OS Independent
Classifier: Topic :: Software Development :: Libraries :: Python Modules
